[
  {
    "id": 6933,
    "city": "Albuquerque",
    "state": "New Mexico",
    "country": "USA"
  },
  { "id": 5542, "city": "Anchorage", "state": "Alaska", "country": "USA" },
  { "id": 6724, "city": "Ann Arbor", "state": "Michigan", "country": "USA" },
  { "id": 6351, "city": "Atlanta", "state": "Georgia", "country": "USA" },
  { "id": 6350, "city": "Athens", "state": "Georgia", "country": "USA" },
  { "id": 7394, "city": "Athens", "state": "Tennessee", "country": "USA" },
  { "id": 7423, "city": "Austin", "state": "Texas", "country": "USA" },
  { "id": 6656, "city": "Baltimore", "state": "Maryland", "country": "USA" },
  {
    "id": 5623,
    "city": "Bakersfield",
    "state": "California",
    "country": "USA"
  },
  { "id": 538, "city": "Barrie", "state": "Ontario", "country": "Canada" },
  { "id": 6693, "city": "Boston", "state": "Massachusetts", "country": "USA" },
  { "id": 424, "city": "Calgary", "state": "Alberta", "country": "Canada" },
  { "id": 7395, "city": "Chattanooga", "state": "Tennessee", "country": "USA" },
  {
    "id": 7032,
    "city": "Charlotte",
    "state": "North Carolina",
    "country": "USA"
  },
  { "id": 6443, "city": "Chicago", "state": "Illinois", "country": "USA" },
  { "id": 6500, "city": "Chicago", "state": "Indiana", "country": "USA" },
  { "id": 7113, "city": "Cincinnati", "state": "Ohio", "country": "USA" },
  { "id": 6797, "city": "Cleveland", "state": "Mississippi", "country": "USA" },
  { "id": 7114, "city": "Cleveland", "state": "Ohio", "country": "USA" },
  { "id": 5697, "city": "Columbia", "state": "California", "country": "USA" },
  {
    "id": 7364,
    "city": "Columbia",
    "state": "South Carolina",
    "country": "USA"
  },
  { "id": 7396, "city": "Columbia", "state": "Tennessee", "country": "USA" },
  { "id": 6357, "city": "Columbus", "state": "Georgia", "country": "USA" },
  { "id": 6501, "city": "Columbus", "state": "Indiana", "country": "USA" },
  { "id": 7116, "city": "Columbus", "state": "Ohio", "country": "USA" },
  { "id": 7439, "city": "Columbus", "state": "Texas", "country": "USA" },
  { "id": 7837, "city": "Columbus", "state": "Wisconsin", "country": "USA" },
  { "id": 7445, "city": "Dallas", "state": "Texas", "country": "USA" },
  { "id": 6195, "city": "Denver", "state": "Colorado", "country": "USA" },
  { "id": 6542, "city": "Des Moines", "state": "Iowa", "country": "USA" },
  { "id": 6732, "city": "Detroit", "state": "Michigan", "country": "USA" },
  { "id": 7205, "city": "Detroit", "state": "Oregon", "country": "USA" },
  { "id": 431, "city": "Edmonton", "state": "Alberta", "country": "Canada" },
  { "id": 5761, "city": "Fairfax", "state": "California", "country": "USA" },
  { "id": 5588, "city": "Fayetteville", "state": "Arkansas", "country": "USA" },
  {
    "id": 7036,
    "city": "Fayetteville",
    "state": "North Carolina",
    "country": "USA"
  },
  { "id": 6294, "city": "Fort Myers", "state": "Florida", "country": "USA" },
  { "id": 7459, "city": "Fort Worth", "state": "Texas", "country": "USA" },
  { "id": 5776, "city": "Fremont", "state": "California", "country": "USA" },
  { "id": 6298, "city": "Gainesville", "state": "Florida", "country": "USA" },
  { "id": 6366, "city": "Gainesville", "state": "Georgia", "country": "USA" },
  { "id": 7670, "city": "Gainesville", "state": "Virginia", "country": "USA" },
  {
    "id": 7040,
    "city": "Greensboro",
    "state": "North Carolina",
    "country": "USA"
  },
  {
    "id": 7041,
    "city": "Greenville",
    "state": "North Carolina",
    "country": "USA"
  },
  {
    "id": 7369,
    "city": "Greenville",
    "state": "South Carolina",
    "country": "USA"
  },
  { "id": 7468, "city": "Greenville", "state": "Texas", "country": "USA" },
  {
    "id": 4154,
    "city": "Guadalajara",
    "state": "Jalisco",
    "country": "Mexico"
  },
  { "id": 551, "city": "Guelph", "state": "Ontario", "country": "Canada" },
  {
    "id": 111,
    "city": "Hamilton",
    "state": "Victoria",
    "country": "Australia"
  },
  { "id": 552, "city": "Hamilton", "state": "Ontario", "country": "Canada" },
  {
    "id": 4302,
    "city": "Hamilton",
    "state": "Waikato",
    "country": "New Zealand"
  },
  { "id": 6842, "city": "Hamilton", "state": "Montana", "country": "USA" },
  {
    "id": 111,
    "city": "Hamilton",
    "state": "Victoria",
    "country": "Australia"
  },
  { "id": 552, "city": "Hamilton", "state": "Ontario", "country": "Canada" },
  {
    "id": 4302,
    "city": "Hamilton",
    "state": "Waikato",
    "country": "New Zealand"
  },
  { "id": 6842, "city": "Hamilton", "state": "Montana", "country": "USA" },
  { "id": 6387, "city": "Honolulu", "state": "Hawaii", "country": "USA" },
  {
    "id": 478,
    "city": "Houston",
    "state": "British Columbia",
    "country": "Canada"
  },
  { "id": 7308, "city": "Houston", "state": "Pennsylvania", "country": "USA" },
  { "id": 7474, "city": "Houston", "state": "Texas", "country": "USA" },
  { "id": 6514, "city": "Indianapolis", "state": "Indiana", "country": "USA" },
  { "id": 5815, "city": "Irvine", "state": "California", "country": "USA" },
  { "id": 6307, "city": "Jacksonville", "state": "Florida", "country": "USA" },
  { "id": 7215, "city": "Jacksonville", "state": "Oregon", "country": "USA" },
  { "id": 6560, "city": "Kansas City", "state": "Kansas", "country": "USA" },
  { "id": 6816, "city": "Kansas City", "state": "Missouri", "country": "USA" },
  { "id": 555, "city": "Kitchener", "state": "Ontario", "country": "Canada" },
  { "id": 89, "city": "Kingston", "state": "Tasmania", "country": "Australia" },
  { "id": 553, "city": "Kingston", "state": "Ontario", "country": "Canada" },
  { "id": 7734, "city": "Kingston", "state": "Washington", "country": "USA" },
  { "id": 6870, "city": "Las Vegas", "state": "Nevada", "country": "USA" },
  { "id": 6948, "city": "Las Vegas", "state": "New Mexico", "country": "USA" },
  { "id": 6577, "city": "Lexington", "state": "Kentucky", "country": "USA" },
  {
    "id": 6705,
    "city": "Lexington",
    "state": "Massachusetts",
    "country": "USA"
  },
  { "id": 6745, "city": "Lexington", "state": "Michigan", "country": "USA" },
  {
    "id": 7052,
    "city": "Lexington",
    "state": "North Carolina",
    "country": "USA"
  },
  { "id": 5589, "city": "Little Rock", "state": "Arkansas", "country": "USA" },
  { "id": 556, "city": "London", "state": "Ontario", "country": "Canada" },
  { "id": 7133, "city": "London", "state": "Ohio", "country": "USA" },
  { "id": 635, "city": "Los Angeles", "state": "Biobio", "country": "Chile" },
  {
    "id": 5876,
    "city": "Los Angeles",
    "state": "California",
    "country": "USA"
  },
  { "id": 6225, "city": "Louisville", "state": "Colorado", "country": "USA" },
  { "id": 6578, "city": "Louisville", "state": "Kentucky", "country": "USA" },
  { "id": 7407, "city": "Louisville", "state": "Tennessee", "country": "USA" },
  { "id": 5533, "city": "Madison", "state": "Alabama", "country": "USA" },
  { "id": 6255, "city": "Madison", "state": "Connecticut", "country": "USA" },
  { "id": 7851, "city": "Madison", "state": "Wisconsin", "country": "USA" },
  {
    "id": 114,
    "city": "Melbourne",
    "state": "Victoria",
    "country": "Australia"
  },
  {
    "id": 4169,
    "city": "Mexico City",
    "state": "Mexico City",
    "country": "Mexico"
  },
  { "id": 6315, "city": "Miami", "state": "Florida", "country": "USA" },
  { "id": 7855, "city": "Milwaukee", "state": "Wisconsin", "country": "USA" },
  { "id": 6782, "city": "Minneapolis", "state": "Minnesota", "country": "USA" },
  { "id": 557, "city": "Mississauga", "state": "Ontario", "country": "Canada" },
  { "id": 5535, "city": "Mobile", "state": "Alabama", "country": "USA" },
  {
    "id": 4187,
    "city": "Monterrey",
    "state": "Nuevo Leon",
    "country": "Mexico"
  },
  { "id": 599, "city": "Montreal", "state": "Quebec", "country": "Canada" },
  {
    "id": 288,
    "city": "Nassau",
    "state": "New Providence",
    "country": "Bahamas"
  },
  { "id": 7413, "city": "Nashville", "state": "Tennessee", "country": "USA" },
  { "id": 5934, "city": "Newark", "state": "California", "country": "USA" },
  { "id": 6464, "city": "Newark", "state": "Illinois", "country": "USA" },
  { "id": 6921, "city": "Newark", "state": "New Jersey", "country": "USA" },
  { "id": 6615, "city": "New Orleans", "state": "Louisiana", "country": "USA" },
  { "id": 6990, "city": "New York", "state": "New York", "country": "USA" },
  { "id": 5949, "city": "Oakland", "state": "California", "country": "USA" },
  {
    "id": 7177,
    "city": "Oklahoma City",
    "state": "Oklahoma",
    "country": "USA"
  },
  { "id": 6321, "city": "Orlando", "state": "Florida", "country": "USA" },
  { "id": 563, "city": "Ottawa", "state": "Ontario", "country": "Canada" },
  { "id": 6327, "city": "Pensacola", "state": "Florida", "country": "USA" },
  {
    "id": 7331,
    "city": "Philadelphia",
    "state": "Pennsylvania",
    "country": "USA"
  },
  { "id": 5571, "city": "Phoenix", "state": "Arizona", "country": "USA" },
  { "id": 7236, "city": "Phoenix", "state": "Oregon", "country": "USA" },
  {
    "id": 7332,
    "city": "Pittsburgh",
    "state": "Pennsylvania",
    "country": "USA"
  },
  { "id": 6648, "city": "Portland", "state": "Maine", "country": "USA" },
  { "id": 7237, "city": "Portland", "state": "Oregon", "country": "USA" },
  {
    "id": 7067,
    "city": "Raleigh",
    "state": "North Carolina",
    "country": "USA"
  },
  { "id": 6787, "city": "Rochester", "state": "Minnesota", "country": "USA" },
  { "id": 7003, "city": "Rochester", "state": "New York", "country": "USA" },
  { "id": 6025, "city": "Sacramento", "state": "California", "country": "USA" },
  { "id": 6926, "city": "Salem", "state": "New Jersey", "country": "USA" },
  { "id": 7241, "city": "Salem", "state": "Oregon", "country": "USA" },
  { "id": 7618, "city": "Salem", "state": "Utah", "country": "USA" },
  { "id": 7619, "city": "Salt Lake City", "state": "Utah", "country": "USA" },
  { "id": 6335, "city": "San Antonio", "state": "Florida", "country": "USA" },
  { "id": 7521, "city": "San Antonio", "state": "Texas", "country": "USA" },
  { "id": 6035, "city": "San Diego", "state": "California", "country": "USA" },
  {
    "id": 6036,
    "city": "San Francisco",
    "state": "California",
    "country": "USA"
  },
  { "id": 6823, "city": "Saint Louis", "state": "Missouri", "country": "USA" },
  { "id": 6791, "city": "Saint Paul", "state": "Minnesota", "country": "USA" },
  {
    "id": 6334,
    "city": "Saint Petersburg",
    "state": "Florida",
    "country": "USA"
  },
  { "id": 6055, "city": "Santa Cruz", "state": "California", "country": "USA" },
  { "id": 7777, "city": "Seattle", "state": "Washington", "country": "USA" },
  {
    "id": 7391,
    "city": "Sioux Falls",
    "state": "South Dakota",
    "country": "USA"
  },
  { "id": 7785, "city": "Spokane", "state": "Washington", "country": "USA" },
  { "id": 7790, "city": "Tacoma", "state": "Washington", "country": "USA" },
  { "id": 6341, "city": "Tampa", "state": "Florida", "country": "USA" },
  { "id": 576, "city": "Toronto", "state": "Ontario", "country": "Canada" },
  { "id": 5582, "city": "Tucson", "state": "Arizona", "country": "USA" },
  { "id": 7184, "city": "Tulsa", "state": "Oklahoma", "country": "USA" },
  {
    "id": 7815,
    "city": "Washington",
    "state": "Washington, D.C.",
    "country": "USA"
  },
  { "id": 577, "city": "Windsor", "state": "Ontario", "country": "Canada" },
  { "id": 6167, "city": "Windsor", "state": "California", "country": "USA" },
  { "id": 515, "city": "Winnipeg", "state": "Manitoba", "country": "Canada" },
  {
    "id": 5,
    "city": "Buenos Aires",
    "state": "Buenos Aires",
    "country": "Argentina"
  },
  { "id": 366, "city": "Campinas", "state": "Sao Paulo", "country": "Brazil" },
  { "id": 391, "city": "Sao Paulo", "state": "Sao Paulo", "country": "Brazil" },
  { "id": 632, "city": "Concepcion", "state": "Biobio", "country": "Chile" },
  {
    "id": 660,
    "city": "Santiago",
    "state": "Santiago Metropolitan",
    "country": "Chile"
  },
  {
    "id": 1088,
    "city": "Medellin",
    "state": "Antioquia",
    "country": "Colombia"
  },
  { "id": 6039, "city": "San Jose", "state": "California", "country": "USA" },
  { "id": 1246, "city": "Quito", "state": "Pichincha", "country": "Ecuador" },
  { "id": 6326, "city": "Panama City", "state": "Florida", "country": "USA" },
  { "id": 4366, "city": "Lima", "state": "Lima", "country": "Peru" },
  { "id": 7132, "city": "Lima", "state": "Ohio", "country": "USA" },
  {
    "id": 1776,
    "city": "Aachen",
    "state": "Nordrhein-Westfalen",
    "country": "Germany"
  },
  {
    "id": 1242,
    "city": "Aalborg",
    "state": "North Denmark Region",
    "country": "Denmark"
  },
  {
    "id": 4234,
    "city": "Amsterdam",
    "state": "North Holland",
    "country": "Netherlands"
  },
  { "id": 6350, "city": "Athens", "state": "Georgia", "country": "USA" },
  { "id": 7394, "city": "Athens", "state": "Tennessee", "country": "USA" },
  { "id": 5045, "city": "Barcelona", "state": "Catalunya", "country": "Spain" },
  { "id": 2242, "city": "Bari", "state": "Apulia", "country": "Italy" },
  {
    "id": 5236,
    "city": "Basel",
    "state": "Basel-City",
    "country": "Switzerland"
  },
  {
    "id": 4674,
    "city": "Belgrade",
    "state": "Central Serbia",
    "country": "Serbia"
  },
  { "id": 2331, "city": "Bergamo", "state": "Lombardy", "country": "Italy" },
  { "id": 4326, "city": "Bergen", "state": "Hordaland", "country": "Norway" },
  { "id": 1687, "city": "Berlin", "state": "Berlin", "country": "Germany" },
  { "id": 5242, "city": "Bern", "state": "Bern", "country": "Switzerland" },
  { "id": 5517, "city": "Birmingham", "state": "Alabama", "country": "USA" },
  {
    "id": 2440,
    "city": "Bolzano-Bozen",
    "state": "Trentino-Alto Adige",
    "country": "Italy"
  },
  {
    "id": 1777,
    "city": "Bonn",
    "state": "Nordrhein-Westfalen",
    "country": "Germany"
  },
  { "id": 4526, "city": "Braga", "state": "Braga", "country": "Portugal" },
  { "id": 4582, "city": "Brasov", "state": "Brasov", "country": "Romania" },
  {
    "id": 4688,
    "city": "Bratislava",
    "state": "Bratislava",
    "country": "Slovakia"
  },
  { "id": 1709, "city": "Bremen", "state": "Bremen", "country": "Germany" },
  { "id": 6966, "city": "Brighton", "state": "New York", "country": "USA" },
  { "id": 6496, "city": "Bristol", "state": "Indiana", "country": "USA" },
  {
    "id": 1200,
    "city": "Brno",
    "state": "South Moravian",
    "country": "Czech Republic"
  },
  {
    "id": 292,
    "city": "Brussels",
    "state": "Brussels Capital",
    "country": "Belgium"
  },
  {
    "id": 4584,
    "city": "Bucharest",
    "state": "Bucuresti",
    "country": "Romania"
  },
  {
    "id": 1917,
    "city": "Budapest",
    "state": "Central Hungary",
    "country": "Hungary"
  },
  { "id": 6659, "city": "Cambridge", "state": "Maryland", "country": "USA" },
  {
    "id": 6696,
    "city": "Cambridge",
    "state": "Massachusetts",
    "country": "USA"
  },
  {
    "id": 1236,
    "city": "Copenhagen",
    "state": "Capital Region",
    "country": "Denmark"
  },
  { "id": 2156, "city": "Cork", "state": "County Cork", "country": "Ireland" },
  { "id": 1847, "city": "Dresden", "state": "Saxony", "country": "Germany" },
  { "id": 2164, "city": "Dublin", "state": "Leinster", "country": "Ireland" },
  { "id": 5732, "city": "Dublin", "state": "California", "country": "USA" },
  {
    "id": 4229,
    "city": "Eindhoven",
    "state": "North Brabant",
    "country": "Netherlands"
  },
  { "id": 79, "city": "Exeter", "state": "Tasmania", "country": "Australia" },
  { "id": 5527, "city": "Florence", "state": "Alabama", "country": "USA" },
  { "id": 7209, "city": "Florence", "state": "Oregon", "country": "USA" },
  {
    "id": 7367,
    "city": "Florence",
    "state": "South Carolina",
    "country": "USA"
  },
  { "id": 2153, "city": "Galway", "state": "Connaught", "country": "Ireland" },
  { "id": 4472, "city": "Gdansk", "state": "Pomerania", "country": "Poland" },
  { "id": 4473, "city": "Gdynia", "state": "Pomerania", "country": "Poland" },
  { "id": 307, "city": "Gent", "state": "Flanders", "country": "Belgium" },
  { "id": 220, "city": "Graz", "state": "Styria", "country": "Austria" },
  {
    "id": 4216,
    "city": "Groningen",
    "state": "Groningen",
    "country": "Netherlands"
  },
  { "id": 1711, "city": "Hamburg", "state": "Hamburg", "country": "Germany" },
  {
    "id": 1616,
    "city": "Heidelberg",
    "state": "Baden-Wuerttemberg",
    "country": "Germany"
  },
  { "id": 1286, "city": "Helsinki", "state": "Uusimaa", "country": "Finland" },
  { "id": 4624, "city": "Iasi", "state": "Iasi", "country": "Romania" },
  {
    "id": 1618,
    "city": "Karlsruhe",
    "state": "Baden-Wuerttemberg",
    "country": "Germany"
  },
  { "id": 4489, "city": "Katowice", "state": "Silesia", "country": "Poland" },
  { "id": 4034, "city": "Kaunas", "state": "Kaunas", "country": "Lithuania" },
  { "id": 4692, "city": "Kosice", "state": "Kosice", "country": "Slovakia" },
  { "id": 5294, "city": "Lausanne", "state": "Vaud", "country": "Switzerland" },
  { "id": 5532, "city": "Leeds", "state": "Alabama", "country": "USA" },
  { "id": 1854, "city": "Leipzig", "state": "Saxony", "country": "Germany" },
  { "id": 314, "city": "Leuven", "state": "Flanders", "country": "Belgium" },
  {
    "id": 1479,
    "city": "Lille",
    "state": "Hauts-de-France",
    "country": "France"
  },
  { "id": 4534, "city": "Lisbon", "state": "Lisbon", "country": "Portugal" },
  {
    "id": 4719,
    "city": "Ljubljana",
    "state": "Osrednjeslovenska",
    "country": "Slovenia"
  },
  {
    "id": 4410,
    "city": "Lodz",
    "state": "Lodz Voivodeship",
    "country": "Poland"
  },
  { "id": 556, "city": "London", "state": "Ontario", "country": "Canada" },
  { "id": 7133, "city": "London", "state": "Ohio", "country": "USA" },
  { "id": 4436, "city": "Lublin", "state": "Lublin", "country": "Poland" },
  { "id": 5278, "city": "Lugano", "state": "Ticino", "country": "Switzerland" },
  {
    "id": 4049,
    "city": "Luxembourg",
    "state": "District de Luxembourg",
    "country": "Luxembourg"
  },
  {
    "id": 1320,
    "city": "Lyon",
    "state": "Auvergne-Rhône-Alpes",
    "country": "France"
  },
  {
    "id": 4222,
    "city": "Maastricht",
    "state": "Limburg",
    "country": "Netherlands"
  },
  { "id": 5117, "city": "Madrid", "state": "Madrid", "country": "Spain" },
  {
    "id": 2322,
    "city": "Modena",
    "state": "Emilia-Romagna",
    "country": "Italy"
  },
  { "id": 4667, "city": "Moscow", "state": "Moscow", "country": "Russia" },
  { "id": 6423, "city": "Moscow", "state": "Idaho", "country": "USA" },
  { "id": 1664, "city": "Munich", "state": "Bavaria", "country": "Germany" },
  {
    "id": 1593,
    "city": "Nantes",
    "state": "Pays de la Loire",
    "country": "France"
  },
  { "id": 2308, "city": "Naples", "state": "Campania", "country": "Italy" },
  { "id": 6317, "city": "Naples", "state": "Florida", "country": "USA" },
  { "id": 6989, "city": "Naples", "state": "New York", "country": "USA" },
  {
    "id": 4671,
    "city": "Novi Sad",
    "state": "Autonomna Pokrajina Vojvodina",
    "country": "Serbia"
  },
  { "id": 1669, "city": "Nuremberg", "state": "Bavaria", "country": "Germany" },
  {
    "id": 1187,
    "city": "Olomouc",
    "state": "Olomoucky",
    "country": "Czech Republic"
  },
  { "id": 1104, "city": "Osijek", "state": "Croatia", "country": "Croatia" },
  { "id": 4334, "city": "Oslo", "state": "Oslo", "country": "Norway" },
  {
    "id": 1176,
    "city": "Ostrava",
    "state": "Moravskoslezsky",
    "country": "Czech Republic"
  },
  { "id": 7144, "city": "Oxford", "state": "Ohio", "country": "USA" },
  {
    "id": 1510,
    "city": "Paris",
    "state": "Ile-de-France",
    "country": "France"
  },
  { "id": 406, "city": "Plovdiv", "state": "Plovdiv", "country": "Bulgaria" },
  { "id": 4548, "city": "Porto", "state": "Porto", "country": "Portugal" },
  {
    "id": 4389,
    "city": "Poznan",
    "state": "Greater Poland",
    "country": "Poland"
  },
  {
    "id": 1199,
    "city": "Prague",
    "state": "Praha",
    "country": "Czech Republic"
  },
  { "id": 7336, "city": "Reading", "state": "Pennsylvania", "country": "USA" },
  { "id": 4030, "city": "Riga", "state": "Riga", "country": "Latvia" },
  { "id": 1111, "city": "Rijeka", "state": "Croatia", "country": "Croatia" },
  { "id": 6373, "city": "Rome", "state": "Georgia", "country": "USA" },
  {
    "id": 4257,
    "city": "Rotterdam",
    "state": "South Holland",
    "country": "Netherlands"
  },
  {
    "id": 6334,
    "city": "Saint Petersburg",
    "state": "Florida",
    "country": "USA"
  },
  {
    "id": 356,
    "city": "Sarajevo",
    "state": "Federation of B H",
    "country": "Bosnia Herzegovina"
  },
  {
    "id": 100,
    "city": "Sheffield",
    "state": "Tasmania",
    "country": "Australia"
  },
  { "id": 4649, "city": "Sibiu", "state": "Sibiu", "country": "Romania" },
  { "id": 4062, "city": "Skopje", "state": "Skopje", "country": "Macedonia" },
  { "id": 410, "city": "Sofia", "state": "Sofia", "country": "Bulgaria" },
  {
    "id": 579,
    "city": "Southampton",
    "state": "Prince Edward Island",
    "country": "Canada"
  },
  { "id": 1116, "city": "Split", "state": "Croatia", "country": "Croatia" },
  { "id": 4342, "city": "Stavanger", "state": "Rogaland", "country": "Norway" },
  {
    "id": 5214,
    "city": "Stockholm",
    "state": "Stockholm",
    "country": "Sweden"
  },
  {
    "id": 1632,
    "city": "Stuttgart",
    "state": "Baden-Wuerttemberg",
    "country": "Germany"
  },
  {
    "id": 4522,
    "city": "Szczecin",
    "state": "West Pomerania",
    "country": "Poland"
  },
  { "id": 1277, "city": "Tampere", "state": "Pirkanmaa", "country": "Finland" },
  { "id": 4658, "city": "Timisoara", "state": "Timis", "country": "Romania" },
  { "id": 1585, "city": "Toulouse", "state": "Occitanie", "country": "France" },
  {
    "id": 2456,
    "city": "Trento",
    "state": "Trentino-Alto Adige",
    "country": "Italy"
  },
  {
    "id": 4343,
    "city": "Trondheim",
    "state": "Sor-Trondelag",
    "country": "Norway"
  },
  {
    "id": 1259,
    "city": "Turku",
    "state": "Finland Proper",
    "country": "Finland"
  },
  {
    "id": 5217,
    "city": "Uppsala",
    "state": "Uppsala län",
    "country": "Sweden"
  },
  {
    "id": 4265,
    "city": "Utrecht",
    "state": "Utrecht",
    "country": "Netherlands"
  },
  { "id": 5175, "city": "Valencia", "state": "Valencia", "country": "Spain" },
  { "id": 6962, "city": "Valencia", "state": "New Mexico", "country": "USA" },
  { "id": 414, "city": "Varna", "state": "Varna", "country": "Bulgaria" },
  { "id": 2490, "city": "Venice", "state": "Veneto", "country": "Italy" },
  { "id": 6140, "city": "Venice", "state": "California", "country": "USA" },
  { "id": 6345, "city": "Venice", "state": "Florida", "country": "USA" },
  { "id": 280, "city": "Vienna", "state": "Vienna", "country": "Austria" },
  { "id": 7685, "city": "Vienna", "state": "Virginia", "country": "USA" },
  { "id": 7825, "city": "Vienna", "state": "West Virginia", "country": "USA" },
  { "id": 4044, "city": "Vilnius", "state": "Vilnius", "country": "Lithuania" },
  { "id": 4459, "city": "Warsaw", "state": "Mazovia", "country": "Poland" },
  {
    "id": 4429,
    "city": "Wroclaw",
    "state": "Lower Silesia",
    "country": "Poland"
  },
  { "id": 611, "city": "York", "state": "Quebec", "country": "Canada" },
  { "id": 7355, "city": "York", "state": "Pennsylvania", "country": "USA" },
  { "id": 7383, "city": "York", "state": "South Carolina", "country": "USA" },
  { "id": 1122, "city": "Zagreb", "state": "Croatia", "country": "Croatia" },
  { "id": 5298, "city": "Zug", "state": "Zug", "country": "Switzerland" },
  { "id": 1963, "city": "Ahmedabad", "state": "Gujarat", "country": "India" },
  { "id": 5397, "city": "Ankara", "state": "Ankara", "country": "Turkey" },
  { "id": 5337, "city": "Bangkok", "state": "Bangkok", "country": "Thailand" },
  { "id": 689, "city": "Beijing", "state": "Beijing", "country": "China" },
  { "id": 5415, "city": "Bursa", "state": "Bursa", "country": "Turkey" },
  { "id": 4774, "city": "Busan", "state": "Busan", "country": "South Korea" },
  {
    "id": 4864,
    "city": "Busan",
    "state": "Gyeongsangnam-do",
    "country": "South Korea"
  },
  { "id": 2035, "city": "Chennai", "state": "Tamil Nadu", "country": "India" },
  {
    "id": 5354,
    "city": "Chiang Mai",
    "state": "Chiang Mai",
    "country": "Thailand"
  },
  { "id": 5183, "city": "Colombo", "state": "Western", "country": "Sri Lanka" },
  { "id": 1956, "city": "Delhi", "state": "Delhi", "country": "India" },
  { "id": 290, "city": "Dhaka", "state": "Dhaka", "country": "Bangladesh" },
  { "id": 724, "city": "Guangzhou", "state": "Guangdong", "country": "China" },
  { "id": 2198, "city": "Haifa", "state": "Haifa", "country": "Israel" },
  {
    "id": 1915,
    "city": "Hong Kong",
    "state": "Hong Kong",
    "country": "Hong Kong"
  },
  { "id": 2036, "city": "Hyderabad", "state": "Telangana", "country": "India" },
  {
    "id": 4351,
    "city": "Islamabad",
    "state": "Islamabad",
    "country": "Pakistan"
  },
  { "id": 5447, "city": "Istanbul", "state": "Istanbul", "country": "Turkey" },
  { "id": 5456, "city": "Izmir", "state": "Izmir", "country": "Turkey" },
  { "id": 2030, "city": "Jaipur", "state": "Rajasthan", "country": "India" },
  { "id": 2061, "city": "Jakarta", "state": "Jakarta", "country": "Indonesia" },
  {
    "id": 2209,
    "city": "Jerusalem",
    "state": "Jerusalem",
    "country": "Israel"
  },
  {
    "id": 4068,
    "city": "Johor Bahru",
    "state": "Johor",
    "country": "Malaysia"
  },
  {
    "id": 5313,
    "city": "Kaohsiung",
    "state": "Kaohsiung",
    "country": "Taiwan"
  },
  { "id": 4361, "city": "Karachi", "state": "Sindh", "country": "Pakistan" },
  {
    "id": 4204,
    "city": "Kathmandu",
    "state": "Central Region",
    "country": "Nepal"
  },
  { "id": 2055, "city": "Kolkata", "state": "West Bengal", "country": "India" },
  {
    "id": 4081,
    "city": "Kuala Lumpur",
    "state": "Kuala Lumpur",
    "country": "Malaysia"
  },
  {
    "id": 4025,
    "city": "Kuwait City",
    "state": "Al Asimah",
    "country": "Kuwait"
  },
  { "id": 4355, "city": "Lahore", "state": "Punjab", "country": "Pakistan" },
  { "id": 1131, "city": "Limassol", "state": "Limassol", "country": "Cyprus" },
  { "id": 2023, "city": "Ludhiana", "state": "Punjab", "country": "India" },
  {
    "id": 289,
    "city": "Manama",
    "state": "Capital Governorate",
    "country": "Bahrain"
  },
  { "id": 2007, "city": "Mumbai", "state": "Maharashtra", "country": "India" },
  { "id": 2008, "city": "Nagpur", "state": "Maharashtra", "country": "India" },
  {
    "id": 2010,
    "city": "Navi Mumbai",
    "state": "Maharashtra",
    "country": "India"
  },
  { "id": 1132, "city": "Nicosia", "state": "Nicosia", "country": "Cyprus" },
  { "id": 2048, "city": "Noida", "state": "Uttar Pradesh", "country": "India" },
  { "id": 5374, "city": "Phuket", "state": "Phuket", "country": "Thailand" },
  { "id": 2013, "city": "Pune", "state": "Maharashtra", "country": "India" },
  { "id": 2234, "city": "Ramat Gan", "state": "Tel Aviv", "country": "Israel" },
  { "id": 4915, "city": "Seoul", "state": "Seoul", "country": "South Korea" },
  { "id": 989, "city": "Shanghai", "state": "Shanghai", "country": "China" },
  { "id": 735, "city": "Shenzhen", "state": "Guangdong", "country": "China" },
  {
    "id": 4682,
    "city": "Singapore",
    "state": "Singapore",
    "country": "Singapore"
  },
  { "id": 5315, "city": "Taipei", "state": "Taipei", "country": "Taiwan" },
  { "id": 2141, "city": "Tehran", "state": "Tehran", "country": "Iran" },
  {
    "id": 1992,
    "city": "Thiruvananthapuram",
    "state": "Kerala",
    "country": "India"
  },
  { "id": 3901, "city": "Tokyo", "state": "Tokyo", "country": "Japan" },
  {
    "id": 4198,
    "city": "Ulaanbaatar",
    "state": "OEvoerhangay",
    "country": "Mongolia"
  },
  {
    "id": 1950,
    "city": "Visakhapatnam",
    "state": "Andhra Pradesh",
    "country": "India"
  },
  {
    "id": 30,
    "city": "Sydney",
    "state": "New South Wales",
    "country": "Australia"
  },
  { "id": 535, "city": "Sydney", "state": "Nova Scotia", "country": "Canada" },
  { "id": 97, "city": "Perth", "state": "Tasmania", "country": "Australia" },
  {
    "id": 111,
    "city": "Hamilton",
    "state": "Victoria",
    "country": "Australia"
  },
  { "id": 552, "city": "Hamilton", "state": "Ontario", "country": "Canada" },
  {
    "id": 4302,
    "city": "Hamilton",
    "state": "Waikato",
    "country": "New Zealand"
  },
  { "id": 6842, "city": "Hamilton", "state": "Montana", "country": "USA" },
  {
    "id": 38,
    "city": "Auckland",
    "state": "Queensland",
    "country": "Australia"
  },
  {
    "id": 114,
    "city": "Melbourne",
    "state": "Victoria",
    "country": "Australia"
  },
  {
    "id": 4280,
    "city": "Christchurch",
    "state": "Canterbury",
    "country": "New Zealand"
  },
  {
    "id": 69,
    "city": "Adelaide",
    "state": "SouthAustralia",
    "country": "Australia"
  },
  { "id": 5652, "city": "Brisbane", "state": "California", "country": "USA" },
  { "id": 86, "city": "Hobart", "state": "Tasmania", "country": "Australia" },
  {
    "id": 580,
    "city": "Wellington",
    "state": "Prince Edward Island",
    "country": "Canada"
  },
  {
    "id": 25,
    "city": "Newcastle",
    "state": "New South Wales",
    "country": "Australia"
  },
  { "id": 5935, "city": "Newcastle", "state": "California", "country": "USA" },
  { "id": 7757, "city": "Newcastle", "state": "Washington", "country": "USA" },
  { "id": 7889, "city": "Newcastle", "state": "Wyoming", "country": "USA" },
  { "id": 1912, "city": "Accra", "state": "Greater Accra", "country": "Ghana" },
  { "id": 1, "city": "Algiers", "state": "Algiers", "country": "Algeria" },
  { "id": 6969, "city": "Cairo", "state": "New York", "country": "USA" },
  {
    "id": 4744,
    "city": "Durban",
    "state": "KwaZulu-Natal",
    "country": "South Africa"
  },
  { "id": 4315, "city": "Lagos", "state": "Lagos", "country": "Nigeria" },
  { "id": 7796, "city": "Vancouver", "state": "Washington", "country": "USA" }
]
